{
  "81001": {
    "earned": true,
    "earned_time": 1724482829
  },
  "81002": {
    "earned": true,
    "earned_time": 1724497516
  },
  "81003": {
    "earned": true,
    "earned_time": 1724501190
  },
  "81004": {
    "earned": true,
    "earned_time": 1724502068
  },
  "81005": {
    "earned": true,
    "earned_time": 1724504236
  },
  "81006": {
    "earned": true,
    "earned_time": 1724523425
  },
  "81007": {
    "earned": true,
    "earned_time": 1724523555
  },
  "81008": {
    "earned": true,
    "earned_time": 1724577511
  },
  "81009": {
    "earned": true,
    "earned_time": 1724578643
  },
  "81010": {
    "earned": true,
    "earned_time": 1725036206
  },
  "81011": {
    "earned": false,
    "earned_time": 0
  },
  "81012": {
    "earned": true,
    "earned_time": 1725132856
  },
  "81013": {
    "earned": true,
    "earned_time": 1725133873
  },
  "81014": {
    "earned": false,
    "earned_time": 0
  },
  "81015": {
    "earned": true,
    "earned_time": 1725314963
  },
  "81016": {
    "earned": true,
    "earned_time": 1725309984
  },
  "81017": {
    "earned": false,
    "earned_time": 0
  },
  "81018": {
    "earned": false,
    "earned_time": 0
  },
  "81019": {
    "earned": true,
    "earned_time": 1725316881
  },
  "81020": {
    "earned": false,
    "earned_time": 0
  },
  "81021": {
    "earned": true,
    "earned_time": 1725392882
  },
  "81022": {
    "earned": false,
    "earned_time": 0
  },
  "81023": {
    "earned": true,
    "earned_time": 1725395156
  },
  "81024": {
    "earned": false,
    "earned_time": 0
  },
  "81025": {
    "earned": false,
    "earned_time": 0
  },
  "81026": {
    "earned": false,
    "earned_time": 0
  },
  "81027": {
    "earned": false,
    "earned_time": 0
  },
  "81028": {
    "earned": false,
    "earned_time": 0
  },
  "81029": {
    "earned": false,
    "earned_time": 0
  },
  "81030": {
    "earned": false,
    "earned_time": 0
  },
  "81031": {
    "earned": false,
    "earned_time": 0
  },
  "81032": {
    "earned": false,
    "earned_time": 0
  },
  "81033": {
    "earned": false,
    "earned_time": 0
  },
  "81034": {
    "earned": false,
    "earned_time": 0
  },
  "81035": {
    "earned": false,
    "earned_time": 0
  },
  "81036": {
    "earned": false,
    "earned_time": 0
  },
  "81037": {
    "earned": false,
    "earned_time": 0
  },
  "81038": {
    "earned": false,
    "earned_time": 0
  },
  "81039": {
    "earned": false,
    "earned_time": 0
  },
  "81040": {
    "earned": false,
    "earned_time": 0
  },
  "81041": {
    "earned": false,
    "earned_time": 0
  },
  "81042": {
    "earned": false,
    "earned_time": 0
  },
  "81043": {
    "earned": false,
    "earned_time": 0
  },
  "81044": {
    "earned": false,
    "earned_time": 0
  },
  "81045": {
    "earned": false,
    "earned_time": 0
  },
  "81046": {
    "earned": false,
    "earned_time": 0
  },
  "81047": {
    "earned": false,
    "earned_time": 0
  },
  "81048": {
    "earned": false,
    "earned_time": 0
  },
  "81049": {
    "earned": false,
    "earned_time": 0
  },
  "81050": {
    "earned": false,
    "earned_time": 0
  },
  "81051": {
    "earned": false,
    "earned_time": 0
  },
  "81052": {
    "earned": false,
    "earned_time": 0
  },
  "81053": {
    "earned": false,
    "earned_time": 0
  },
  "81054": {
    "earned": false,
    "earned_time": 0
  },
  "81055": {
    "earned": false,
    "earned_time": 0
  },
  "81056": {
    "earned": false,
    "earned_time": 0
  },
  "81057": {
    "earned": false,
    "earned_time": 0
  },
  "81058": {
    "earned": false,
    "earned_time": 0
  },
  "81059": {
    "earned": false,
    "earned_time": 0
  },
  "81060": {
    "earned": false,
    "earned_time": 0
  },
  "81061": {
    "earned": false,
    "earned_time": 0
  },
  "81062": {
    "earned": false,
    "earned_time": 0
  },
  "81063": {
    "earned": false,
    "earned_time": 0
  },
  "81064": {
    "earned": false,
    "earned_time": 0
  },
  "81065": {
    "earned": false,
    "earned_time": 0
  },
  "81066": {
    "earned": false,
    "earned_time": 0
  },
  "81067": {
    "earned": false,
    "earned_time": 0
  },
  "81068": {
    "earned": false,
    "earned_time": 0
  },
  "81069": {
    "earned": false,
    "earned_time": 0
  },
  "81070": {
    "earned": false,
    "earned_time": 0
  },
  "81071": {
    "earned": false,
    "earned_time": 0
  },
  "81072": {
    "earned": false,
    "earned_time": 0
  },
  "81073": {
    "earned": false,
    "earned_time": 0
  },
  "81074": {
    "earned": false,
    "earned_time": 0
  },
  "81075": {
    "earned": false,
    "earned_time": 0
  },
  "81076": {
    "earned": false,
    "earned_time": 0
  },
  "81077": {
    "earned": false,
    "earned_time": 0
  },
  "81078": {
    "earned": false,
    "earned_time": 0
  },
  "81079": {
    "earned": false,
    "earned_time": 0
  },
  "81080": {
    "earned": false,
    "earned_time": 0
  },
  "81081": {
    "earned": false,
    "earned_time": 0
  }
}